{"content":{"settings":"{\n    \"cmake.parallelJobs\": 8,\n    \"markdown.extension.toc.levels\": \"2..6\",\n    \"files.associations\": {\n        \"filesystem\": \"cpp\",\n        \"cctype\": \"cpp\",\n        \"clocale\": \"cpp\",\n        \"cmath\": \"cpp\",\n        \"csetjmp\": \"cpp\",\n        \"csignal\": \"cpp\",\n        \"cstdarg\": \"cpp\",\n        \"cstddef\": \"cpp\",\n        \"cstdio\": \"cpp\",\n        \"cstdlib\": \"cpp\",\n        \"cstring\": \"cpp\",\n        \"ctime\": \"cpp\",\n        \"cwchar\": \"cpp\",\n        \"cwctype\": \"cpp\",\n        \"array\": \"cpp\",\n        \"atomic\": \"cpp\",\n        \"strstream\": \"cpp\",\n        \"*.tcc\": \"cpp\",\n        \"bitset\": \"cpp\",\n        \"cfenv\": \"cpp\",\n        \"chrono\": \"cpp\",\n        \"cinttypes\": \"cpp\",\n        \"codecvt\": \"cpp\",\n        \"complex\": \"cpp\",\n        \"condition_variable\": \"cpp\",\n        \"cstdint\": \"cpp\",\n        \"cuchar\": \"cpp\",\n        \"deque\": \"cpp\",\n        \"forward_list\": \"cpp\",\n        \"list\": \"cpp\",\n        \"unordered_map\": \"cpp\",\n        \"unordered_set\": \"cpp\",\n        \"vector\": \"cpp\",\n        \"exception\": \"cpp\",\n        \"algorithm\": \"cpp\",\n        \"functional\": \"cpp\",\n        \"iterator\": \"cpp\",\n        \"map\": \"cpp\",\n        \"memory\": \"cpp\",\n        \"memory_resource\": \"cpp\",\n        \"numeric\": \"cpp\",\n        \"optional\": \"cpp\",\n        \"random\": \"cpp\",\n        \"ratio\": \"cpp\",\n        \"regex\": \"cpp\",\n        \"set\": \"cpp\",\n        \"string\": \"cpp\",\n        \"string_view\": \"cpp\",\n        \"system_error\": \"cpp\",\n        \"tuple\": \"cpp\",\n        \"type_traits\": \"cpp\",\n        \"utility\": \"cpp\",\n        \"hash_map\": \"cpp\",\n        \"hash_set\": \"cpp\",\n        \"slist\": \"cpp\",\n        \"fstream\": \"cpp\",\n        \"future\": \"cpp\",\n        \"initializer_list\": \"cpp\",\n        \"iomanip\": \"cpp\",\n        \"iosfwd\": \"cpp\",\n        \"iostream\": \"cpp\",\n        \"istream\": \"cpp\",\n        \"limits\": \"cpp\",\n        \"mutex\": \"cpp\",\n        \"new\": \"cpp\",\n        \"ostream\": \"cpp\",\n        \"scoped_allocator\": \"cpp\",\n        \"shared_mutex\": \"cpp\",\n        \"sstream\": \"cpp\",\n        \"stdexcept\": \"cpp\",\n        \"streambuf\": \"cpp\",\n        \"thread\": \"cpp\",\n        \"typeindex\": \"cpp\",\n        \"typeinfo\": \"cpp\",\n        \"valarray\": \"cpp\",\n        \"__nullptr\": \"cpp\",\n        \"*.in\": \"cpp\",\n        \"locale\": \"cpp\",\n        \"variant\": \"cpp\",\n        \"__split_buffer\": \"cpp\",\n        \"any\": \"cpp\",\n        \"bit\": \"cpp\",\n        \"charconv\": \"cpp\",\n        \"__hash_table\": \"cpp\"\n    },\n    \"python.defaultInterpreterPath\": \"/usr/bin/python3\",\n    \"cmake.allowCommentsInPresetsFile\": true\n}","tasks":"{\n    // See https://go.microsoft.com/fwlink/?LinkId=733558\n    // for the documentation about the tasks.json format\n    \"version\": \"2.0.0\",\n    \"tasks\": [\n        {\n            \"label\": \"Setup All\",\n            \"type\": \"shell\",\n            \"options\": {\n                \"cwd\": \"${workspaceFolder}\"\n            },\n            \"dependsOrder\": \"sequence\",\n            \"dependsOn\": [\n                \"Source requirements.txt\",\n                \"Source setup.py\",\n                \"Proto requirements.txt\",\n                \"Proto setup.py\",\n                \"Examples requirements.txt\",\n                \"Examples setup.py\"\n            ],\n            \"command\": \"echo 'Finished Setup All'\",\n            \"problemMatcher\": []\n        },\n        {\n            \"label\": \"Source requirements.txt\",\n            \"type\": \"shell\",\n            \"options\": {\n                \"cwd\": \"${workspaceFolder}/Source\"\n            },\n            \"command\": \"python3 -m pip install --upgrade pip  &&  python3 -m pip install -r requirements.txt\"\n        },\n        {\n            \"label\": \"Examples requirements.txt\",\n            \"type\": \"shell\",\n            \"options\": {\n                \"cwd\": \"${workspaceFolder}/Examples\"\n            },\n            \"command\": \"python3 -m pip install --upgrade pip  &&  python3 -m pip install -r requirements.txt\"\n        },\n        {\n            \"label\": \"Proto requirements.txt\",\n            \"type\": \"shell\",\n            \"options\": {\n                \"cwd\": \"${workspaceFolder}/Examples/proto\"\n            },\n            \"command\": \"python3 -m pip install --upgrade pip  &&  python3 -m pip install -r requirements.txt\"\n        },\n        {\n            \"label\": \"Source setup.py\",\n            \"type\": \"shell\",\n            \"options\": {\n                \"cwd\": \"${workspaceFolder}/Source\"\n            },\n            \"command\": \"python3 setup.py develop --user\"\n        },\n        {\n            \"label\": \"Examples setup.py\",\n            \"type\": \"shell\",\n            \"options\": {\n                \"cwd\": \"${workspaceFolder}/Examples\"\n            },\n            \"command\": \"python3 setup.py develop --user\"\n        },\n        {\n            \"label\": \"Proto setup.py\",\n            \"type\": \"shell\",\n            \"options\": {\n                \"cwd\": \"${workspaceFolder}/Examples/proto\"\n            },\n            \"command\": \"python3 setup_av.py develop --user && python3 setup_progeny.py develop --user\"\n        }\n    ]\n}","launch":"{\n  // Use IntelliSense to learn about possible attributes.\n  // Hover to view descriptions of existing attributes.\n  // For more information, visit: https://go.microsoft.com/fwlink/?linkid=830387\n  \"version\": \"0.2.0\",\n  \"configurations\": [\n    {\n      \"name\": \"Psauron\",\n      \"type\": \"cppdbg\",\n      \"request\": \"launch\",\n      \"program\": \"${workspaceFolder}/Build/${command:cmake.buildType}/bin/sauron_scheduler_client\",\n      \"args\": [\n        \"--scheduler_host=0.0.0.0:7791\",\n        \"--processor_group=0.0\",\n        \"--display_name=psauron_debug\"\n      ],\n      \"stopAtEntry\": false,\n      \"cwd\": \"${workspaceFolder}/.graphs\",\n      // TODO this is a temporary fix to prevent debugger from exiting on segfault.\n      \"environment\": [{\"name\": \"MALLOC_CHECK_\", \"value\": \"2\"},\n                      {\"name\": \"GLOG_logtostderr\", \"value\": \"1\"},\n                      {\"name\": \"GLOG_stderrthreshold\", \"value\": \"0\"},\n                      {\"name\": \"GLOG_v\", \"value\": \"3\"}],\n      \"externalConsole\": false,\n      \"MIMode\": \"gdb\",\n      \"setupCommands\": [\n        {\n          \"description\": \"Enable pretty-printing for gdb\",\n          \"text\": \"-enable-pretty-printing\",\n          \"ignoreFailures\": true\n        }\n      ],\n      \"presentation\": {\n        \"group\": \"Tests\"\n      }\n    },\n    {\n      \"name\": \"Boron\",\n      \"type\": \"cppdbg\",\n      \"request\": \"launch\",\n      \"program\": \"${workspaceFolder}/Build/${command:cmake.buildType}/bin/boron\",\n      \"args\": [\n        \"--grpc_addr=0.0.0.0:50051\",\n        \"--graph_dir=${workspaceFolder}/.graphs\"\n      ],\n      \"cwd\": \"${workspaceFolder}/.graphs\",\n      \"stopAtEntry\": false,\n      // TODO this is a temporary fix to prevent debugger from exiting on segfault.\n      \"environment\": [{\"name\": \"MALLOC_CHECK_\", \"value\": \"2\"},\n                      {\"name\": \"GLOG_logtostderr\", \"value\": \"1\"},\n                      {\"name\": \"GLOG_stderrthreshold\", \"value\": \"0\"},\n                      {\"name\": \"GLOG_v\", \"value\": \"3\"}\n                      // {\"name\": \"SPOTR_DEFAULT_TRT_TACTIC_SOURCES_BITMASK\", \"value\": \"my custome ones\", }\n                    ],\n      \"externalConsole\": false,\n      \"MIMode\": \"gdb\",\n      \"setupCommands\": [\n        {\n          \"description\": \"Enable pretty-printing for gdb\",\n          \"text\": \"-enable-pretty-printing\",\n          \"ignoreFailures\": true\n        }\n      ],\n      \"presentation\": {\n        \"group\": \"Tests\"\n      }\n    },\n    {\n      \"name\": \"Sauron\",\n      \"type\": \"cppdbg\",\n      \"request\": \"launch\",\n      \"program\": \"${workspaceFolder}/Build/${command:cmake.buildType}/bin/sauron\",\n      \"args\": [\n        \"--graph_filename=/workspaces/spotrflow/.graphs/person-vehicle-multi-attr-2023-03-01/person-vehicle-multi-attr-2023-03-01.pb\",\n        \"--source_name=\\\"test\\\"\",\n        \"--video_filename=/host/home/jmolloy/Downloads/20230712-194327-Medium-4-[04]-Safire-DLTV-range-scan.ts\",\n        \"--klv_host=udp://239.0.0.1:3456\"\n      ],\n      \"stopAtEntry\": false,\n      \"cwd\": \"${workspaceFolder}/.graphs\",\n      // TODO this is a temporary fix to prevent debugger from exiting on segfault.\n      \"environment\": [{\"name\": \"MALLOC_CHECK_\", \"value\": \"2\"},\n                      {\"name\": \"GLOG_logtostderr\", \"value\": \"1\"},\n                      {\"name\": \"GLOG_stderrthreshold\", \"value\": \"0\"},\n                      {\"name\": \"GLOG_v\", \"value\": \"3\"}],\n      \"externalConsole\": false,\n      \"MIMode\": \"gdb\",\n      \"setupCommands\": [\n        {\n          \"description\": \"Enable pretty-printing for gdb\",\n          \"text\": \"-enable-pretty-printing\",\n          \"ignoreFailures\": true\n        }\n      ],\n      \"presentation\": {\n        \"group\": \"Tests\"\n      }\n    },\n    {\n      \"name\": \"Centernet tests\",\n      \"type\": \"cppdbg\",\n      \"request\": \"launch\",\n      \"program\": \"${workspaceFolder}/Build/${command:cmake.buildType}/bin/centernet7_tests\",\n      \"args\": [],\n      \"stopAtEntry\": false,\n      \"cwd\": \"${workspaceFolder}/Build/${command:cmake.buildType}/bin\",\n      // TODO this is a temporary fix to prevent debugger from exiting on segfault.\n      \"environment\": [\n        {\n          \"name\": \"MALLOC_CHECK_\",\n          \"value\": \"2\"\n        },\n        {\n          \"name\": \"GLOG_logtostderr\",\n          \"value\": \"1\"\n        },\n        {\n          \"name\": \"GLOG_stderrthreshold\",\n          \"value\": \"0\"\n        },\n        {\n          \"name\": \"GLOG_v\",\n          \"value\": \"3\"\n        }\n      ],\n      \"externalConsole\": false,\n      \"MIMode\": \"gdb\",\n      \"setupCommands\": [\n        {\n          \"description\": \"Enable pretty-printing for gdb\",\n          \"text\": \"-enable-pretty-printing\",\n          \"ignoreFailures\": true\n        }\n      ],\n      \"presentation\": {\n        \"group\": \"Tests\"\n      }\n    },\n    {\n      \"name\": \"Tracking tests\",\n      \"type\": \"cppdbg\",\n      \"request\": \"launch\",\n      \"program\": \"${workspaceFolder}/Build/${command:cmake.buildType}/bin/spotrflow_tracking_tests\",\n      \"args\": [],\n      \"stopAtEntry\": false,\n      \"cwd\": \"${workspaceFolder}/Build/${command:cmake.buildType}/bin\",\n      \"environment\": [\n        {\n          \"name\": \"MALLOC_CHECK_\",\n          \"value\": \"2\"\n        },\n        {\n          \"name\": \"GLOG_logtostderr\",\n          \"value\": \"1\"\n        },\n        {\n          \"name\": \"GLOG_stderrthreshold\",\n          \"value\": \"0\"\n        },\n        {\n          \"name\": \"GLOG_v\",\n          \"value\": \"3\"\n        }\n      ],\n      \"externalConsole\": false,\n      \"MIMode\": \"gdb\",\n      \"setupCommands\": [\n        {\n          \"description\": \"Enable pretty-printing for gdb\",\n          \"text\": \"-enable-pretty-printing\",\n          \"ignoreFailures\": true\n        }\n      ],\n      \"presentation\": {\n        \"group\": \"Tests\"\n      }\n    },\n    {\n      \"name\": \"Processor Factory tests\",\n      \"type\": \"cppdbg\",\n      \"request\": \"launch\",\n      \"program\": \"${workspaceFolder}/Build/${command:cmake.buildType}/bin/sauron_processor_factory_tests\",\n      \"args\": [],\n      \"stopAtEntry\": false,\n      \"cwd\": \"${workspaceFolder}/Build/${command:cmake.buildType}/bin\",\n      \"environment\": [\n        {\n          \"name\": \"MALLOC_CHECK_\",\n          \"value\": \"2\"\n        },\n        {\n          \"name\": \"GLOG_logtostderr\",\n          \"value\": \"1\"\n        },\n        {\n          \"name\": \"GLOG_stderrthreshold\",\n          \"value\": \"0\"\n        },\n        {\n          \"name\": \"GLOG_v\",\n          \"value\": \"3\"\n        }\n      ],\n      \"externalConsole\": false,\n      \"MIMode\": \"gdb\",\n      \"setupCommands\": [\n        {\n          \"description\": \"Enable pretty-printing for gdb\",\n          \"text\": \"-enable-pretty-printing\",\n          \"ignoreFailures\": true\n        }\n      ],\n      \"presentation\": {\n        \"group\": \"Tests\"\n      }\n    },\n    {\n      \"name\": \"Graph Manager\",\n      \"type\": \"go\",\n      \"request\": \"launch\",\n      \"mode\": \"auto\",\n      \"program\": \"${workspaceFolder}/Deployment/GraphManager/Source/main.go\"\n    }\n  ]\n}"}}